pollination/abnt_nbr_15575_daylight/__init__.py
pollination/abnt_nbr_15575_daylight/_prepare_folder.py
pollination/abnt_nbr_15575_daylight/_visualization.py
pollination/abnt_nbr_15575_daylight/entry.py
pollination/abnt_nbr_15575_daylight/point_in_time/_illuminance.py
pollination_abnt_nbr_15575_daylight-0.0.20.dist-info/LICENSE
pollination_abnt_nbr_15575_daylight-0.0.20.dist-info/METADATA
pollination_abnt_nbr_15575_daylight-0.0.20.dist-info/WHEEL
pollination_abnt_nbr_15575_daylight-0.0.20.dist-info/top_level.txt
pollination_abnt_nbr_15575_daylight-0.0.20.dist-info/RECORD
