Metadata-Version: 2.1
Name: pollination-abnt-nbr-15575-daylight
Version: 0.0.20
Summary: Evaluate ABNT NBR 15575 using point-in-time illuminance.
Home-page: https://github.com/pollination/abnt-nbr-15575-daylight
Author: pollination
Author-email: info@pollination.solutions
Maintainer: mikkel, pollination
Maintainer-email: mikkel@ladybug.tools, info@pollination.solutions
License: PolyForm Shield License 1.0.0, https://polyformproject.org/wp-content/uploads/2020/06/PolyForm-Shield-1.0.0.txt
Project-URL: icon, https://raw.githubusercontent.com/ladybug-tools/artwork/master/icons_components/honeybee/png/abntdaylight.png
Project-URL: docker, https://hub.docker.com/r/ladybugtools/honeybee-radiance
Keywords: honeybee,radiance,abnt,nbr,15575,daylight,illuminance
License-File: LICENSE
Requires-Dist: pollination-honeybee-radiance (==0.22.63)
Requires-Dist: pollination-honeybee-radiance-postprocess (==0.0.68)
Requires-Dist: pollination-path (==0.3.2)
Requires-Dist: pollination-alias (==0.11.11)
Requires-Dist: pollination-honeybee-display (==0.1.17)
